mdutils/__init__.py
mdutils/mdutils.py
mdutils/fileutils/__init__.py
mdutils/fileutils/fileutils.py
mdutils/tools/Header.py
mdutils/tools/Html.py
mdutils/tools/Image.py
mdutils/tools/Link.py
mdutils/tools/MDList.py
mdutils/tools/Table.py
mdutils/tools/TableOfContents.py
mdutils/tools/TextUtils.py
mdutils/tools/__init__.py
mdutils-1.8.0.dist-info/licenses/LICENSE.txt
mdutils-1.8.0.dist-info/METADATA
mdutils-1.8.0.dist-info/WHEEL
mdutils-1.8.0.dist-info/top_level.txt
mdutils-1.8.0.dist-info/RECORD
