Metadata-Version: 2.4
Name: mdutils
Version: 1.8.0
Summary: Useful package for creating Markdown files while executing python code.
Home-page: https://github.com/didix21/mdutils
Author: Didac Coll
Author-email: didaccoll_93@hotmail.com
Maintainer: Didac Coll
Maintainer-email: didaccoll_93@hotmail.com
License: MIT
Project-URL: Documentation, http://mdutils.readthedocs.io
Project-URL: Say Thanks!, https://github.com/didix21/
Project-URL: Source, https://github.com/didix21/mdutils
Platform: Python 3.6
Platform: Python 3.7
Platform: Python 3.8
Classifier: Development Status :: 5 - Production/Stable
Classifier: Operating System :: OS Independent
Classifier: Programming Language :: Python
Classifier: Programming Language :: Python :: 3.6
Classifier: Programming Language :: Python :: 3.7
Classifier: Programming Language :: Python :: 3.8
Classifier: Topic :: Utilities
Classifier: Topic :: Software Development :: Documentation
Classifier: Topic :: Text Processing :: Markup
Classifier: License :: OSI Approved :: MIT License
License-File: LICENSE.txt
Dynamic: author
Dynamic: author-email
Dynamic: classifier
Dynamic: description
Dynamic: home-page
Dynamic: license
Dynamic: license-file
Dynamic: maintainer
Dynamic: maintainer-email
Dynamic: platform
Dynamic: project-url
Dynamic: summary
